[
  {
    "name": "Yehuda Tenenbaum",
    "email": "yehuda@y10tax.com",
    "firm": "55",
    "contribPts": 0,
    "referrals": 0,
    "boosterPts": 0,
    "specialPts": 0,
    "totalPts": 55,
    "level": "Visionary"
  },
  {
    "name": "Gustavo Blanco",
    "email": "gustavoblanco@calderonblancocpa.com",
    "firm": "47",
    "contribPts": 0,
    "referrals": 0,
    "boosterPts": 0,
    "specialPts": 0,
    "totalPts": 47,
    "level": "Trailblazer"
  },
  {
    "name": "Taina Lopes Costa",
    "email": "taina.costa@bizagile.us",
    "firm": "14",
    "contribPts": 0,
    "referrals": 0,
    "boosterPts": 0,
    "specialPts": 0,
    "totalPts": 14,
    "level": "Advocate"
  },
  {
    "name": "Kelly Rohrs",
    "email": "kelly@krohrscpa.com",
    "firm": "1",
    "contribPts": 0,
    "referrals": 0,
    "boosterPts": 0,
    "specialPts": 0,
    "totalPts": 1,
    "level": "Advocate"
  },
  {
    "name": "Ryan Elblein",
    "email": "Ryan.Elblein@Gmail.com",
    "firm": "1",
    "contribPts": 0,
    "referrals": 0,
    "boosterPts": 0,
    "specialPts": 0,
    "totalPts": 1,
    "level": "Advocate"
  },
  {
    "name": "Mary Crislyn Mana-ay Maravillosa",
    "email": "michael@dissectingthedeal.com",
    "firm": "2",
    "contribPts": 0,
    "referrals": 0,
    "boosterPts": 0,
    "specialPts": 0,
    "totalPts": 2,
    "level": "Advocate"
  }
]